{
  "sprite_sheet": "data/user/saves/save_0/sprite_sheet.png",
  "portrait": "data/user/saves/save_0/portrait.png",
  "name": "Gris",
  "pronoun": "ella",
  "time": 0,
  "money": 200,
  "inventory": {
    "cable": 3,
    "connector": 6,
    "cable_crossover_3": 6,
    "cable_straight_3": 6
  },
  "tutorials": {
    "cables": false,
    "subnetting": false,
    "routing": false
  },
  "tasks": {
    "meet_kat": true,
    "mysteries_of_celestia": false,
    "meet_chencho": true,
    "meet_roy": true,
    "create_straight_cable": true,
    "roy_straight_cable": true,
    "create_crossover_cable": true,
    "roy_crossover_cable": true,
    "meet_ale": false
  },
  "status": {}
}